<?xml version="1.0" encoding="UTF-8"?><record_update sys_domain="global" table="sys_app_module">
    <sys_app_module action="DELETE">
        <active>true</active>
        <application/>
        <assessment/>
        <device_type/>
        <filter/>
        <hint/>
        <homepage/>
        <image/>
        <link_type>LIST</link_type>
        <map_page/>
        <mobile_title>Trainees</mobile_title>
        <mobile_view_name>Mobile</mobile_view_name>
        <name>x_167994_training_trainee</name>
        <order/>
        <override_menu_roles>false</override_menu_roles>
        <query/>
        <report/>
        <roles>x_167994_training.trainee_user</roles>
        <sys_class_name>sys_app_module</sys_class_name>
        <sys_created_by>admin</sys_created_by>
        <sys_created_on>2021-07-12 16:22:03</sys_created_on>
        <sys_domain>global</sys_domain>
        <sys_domain_path>/</sys_domain_path>
        <sys_id>0ab9683d071130103676f85c7c1ed0bd</sys_id>
        <sys_mod_count>0</sys_mod_count>
        <sys_name>Trainees</sys_name>
        <sys_overrides/>
        <sys_package display_value="Training Tracker" source="x_167994_training">b9a77c3c2f1130101caaff1df699b687</sys_package>
        <sys_policy/>
        <sys_scope display_value="Training Tracker">b9a77c3c2f1130101caaff1df699b687</sys_scope>
        <sys_update_name>sys_app_module_0ab9683d071130103676f85c7c1ed0bd</sys_update_name>
        <sys_updated_by>admin</sys_updated_by>
        <sys_updated_on>2021-07-12 16:22:03</sys_updated_on>
        <timeline_page/>
        <title>Trainees</title>
        <uncancelable>false</uncancelable>
        <view_name/>
        <window_name/>
    </sys_app_module>
    <sys_update_version action="INSERT_OR_UPDATE">
        <action>DELETE</action>
        <application display_value="Training Tracker">b9a77c3c2f1130101caaff1df699b687</application>
        <file_path/>
        <instance_id>3ea1d3cadb3810907527d7c8f4961931</instance_id>
        <instance_name>dev103912</instance_name>
        <name>sys_app_module_0ab9683d071130103676f85c7c1ed0bd</name>
        <payload><![CDATA[<?xml version="1.0" encoding="UTF-8"?><record_update sys_domain="global" table="sys_app_module"><sys_app_module action="INSERT_OR_UPDATE"><active>true</active><application/><assessment/><device_type/><filter/><hint/><homepage/><image/><link_type>LIST</link_type><map_page/><mobile_title>Trainees</mobile_title><mobile_view_name>Mobile</mobile_view_name><name>x_167994_training_trainee</name><order/><override_menu_roles>false</override_menu_roles><query/><report/><roles>x_167994_training.trainee_user</roles><sys_class_name>sys_app_module</sys_class_name><sys_created_by>admin</sys_created_by><sys_created_on>2021-07-12 16:22:03</sys_created_on><sys_domain>global</sys_domain><sys_domain_path>/</sys_domain_path><sys_id>0ab9683d071130103676f85c7c1ed0bd</sys_id><sys_mod_count>0</sys_mod_count><sys_name>Trainees</sys_name><sys_overrides/><sys_package display_value="Training Tracker" source="x_167994_training">b9a77c3c2f1130101caaff1df699b687</sys_package><sys_policy/><sys_scope display_value="Training Tracker">b9a77c3c2f1130101caaff1df699b687</sys_scope><sys_update_name>sys_app_module_0ab9683d071130103676f85c7c1ed0bd</sys_update_name><sys_updated_by>admin</sys_updated_by><sys_updated_on>2021-07-12 16:22:03</sys_updated_on><timeline_page/><title>Trainees</title><uncancelable>false</uncancelable><view_name/><window_name/></sys_app_module></record_update>]]></payload>
        <payload_hash>689044824</payload_hash>
        <record_name>Trainees</record_name>
        <reverted_from/>
        <source>fdd041f0075130103676f85c7c1ed0ce</source>
        <source_table>sys_update_set</source_table>
        <state>previous</state>
        <sys_created_by>admin</sys_created_by>
        <sys_created_on>2021-07-12 18:24:40</sys_created_on>
        <sys_id>1ac50571079130103676f85c7c1ed0cc</sys_id>
        <sys_mod_count>0</sys_mod_count>
        <sys_recorded_at>17a9bf6ce120000001</sys_recorded_at>
        <sys_updated_by>admin</sys_updated_by>
        <sys_updated_on>2021-07-12 18:24:40</sys_updated_on>
        <type>Module</type>
        <update_guid>96c505719891301003a390ebeb3fc3cc</update_guid>
        <update_guid_history>96c505719891301003a390ebeb3fc3cc:0,86b9683def11301069596dafe85379c0:-1491443500</update_guid_history>
    </sys_update_version>
    <sys_metadata_delete action="INSERT_OR_UPDATE">
        <sys_audit_delete display_value="">4f06c971079130103676f85c7c1ed0d7</sys_audit_delete>
        <sys_class_name>sys_metadata_delete</sys_class_name>
        <sys_created_by>admin</sys_created_by>
        <sys_created_on>2021-07-12 18:25:49</sys_created_on>
        <sys_db_object display_value="" name="sys_app_module">sys_app_module</sys_db_object>
        <sys_id>2af6079d9b734a8e9943e4d415c92064</sys_id>
        <sys_metadata>0ab9683d071130103676f85c7c1ed0bd</sys_metadata>
        <sys_mod_count>0</sys_mod_count>
        <sys_name>Trainees</sys_name>
        <sys_package display_value="Training Tracker" source="x_167994_training">b9a77c3c2f1130101caaff1df699b687</sys_package>
        <sys_parent/>
        <sys_policy/>
        <sys_scope display_value="Training Tracker">b9a77c3c2f1130101caaff1df699b687</sys_scope>
        <sys_scope_delete display_value="">26ee68e2f64c4a939368209eabc9ae39</sys_scope_delete>
        <sys_update_name>sys_app_module_0ab9683d071130103676f85c7c1ed0bd</sys_update_name>
        <sys_update_version display_value="sys_app_module_0ab9683d071130103676f85c7c1ed0bd">1ac50571079130103676f85c7c1ed0cc</sys_update_version>
        <sys_updated_by>admin</sys_updated_by>
        <sys_updated_on>2021-07-12 18:25:49</sys_updated_on>
    </sys_metadata_delete>
</record_update>
